udprecv.py
udprecv-0.0.1.data/scripts/udprecv.py
udprecv-0.0.1.dist-info/DESCRIPTION.rst
udprecv-0.0.1.dist-info/METADATA
udprecv-0.0.1.dist-info/metadata.json
udprecv-0.0.1.dist-info/RECORD
udprecv-0.0.1.dist-info/top_level.txt
udprecv-0.0.1.dist-info/WHEEL
